vatsim/__init__.py
vatsim/status.py
vatstat-0.0.7.dist-info/LICENSE
vatstat-0.0.7.dist-info/METADATA
vatstat-0.0.7.dist-info/WHEEL
vatstat-0.0.7.dist-info/top_level.txt
vatstat-0.0.7.dist-info/RECORD
