Metadata-Version: 2.1
Name: vatstat
Version: 0.0.7
Summary: python api that makes interacting with the VATSIM data less painful and more pragmatic.
Home-page: https://github.com/BIGjuevos/vatstat
Author: Ryan Null
Author-email: ryan.null@gmail.com
License: UNKNOWN
Platform: UNKNOWN
Classifier: Programming Language :: Python :: 3
Classifier: License :: OSI Approved :: MIT License
Classifier: Operating System :: OS Independent
